posix_or_nt.py
posix_or_nt-0.1.0.dist-info/licenses/LICENSE
posix_or_nt-0.1.0.dist-info/METADATA
posix_or_nt-0.1.0.dist-info/WHEEL
posix_or_nt-0.1.0.dist-info/top_level.txt
posix_or_nt-0.1.0.dist-info/RECORD
