Metadata-Version: 2.4
Name: posix-or-nt
Version: 0.1.0
Summary: Determine whether the current Python interpreter is running on a POSIX-like or Windows NT platform---even when `os.name` is `java` (Jython).
Author-email: Jifeng Wu <jifengwu2k@gmail.com>
License-Expression: MIT
Project-URL: Homepage, https://github.com/jifengwu2k/posix-or-nt
Project-URL: Bug Tracker, https://github.com/jifengwu2k/posix-or-nt/issues
Classifier: Programming Language :: Python
Classifier: Operating System :: OS Independent
Requires-Python: >=2
License-File: LICENSE
Dynamic: license-file
